<?xml version="1.0" encoding="UTF-8" standalone="no"?>
<pk><wd nm="tstoconfigurethecalleridthatappearsonarecipient" rd="78,0:275"/><wd nm="ttach" rd="19,0:649|20,0:1663|22,0:822|77,0:22099|79,0:9920"/><wd nm="ttached" rd="1,0:1501|22,0:980|24,0:1083"/><wd nm="ttachments" rd="20,8:482,1586,1618,1849,2096|47,0:473|77,0:901,22023,22054,22285|79,0:9798,10019,10087,10135"/><wd nm="tte" rd="51,0:1585|68,0:5157"/><wd nm="tted" rd="32,0:2945,2967|36,0:762,784|38,0:1772,1816|40,0:2468,2490|58,0:219|60,0:1394|71,0:622,658,808,1540,1576,2584,2620|79,0:9999"/><wd nm="ttedtothesystem" rd="78,0:430"/><wd nm="ttempt" rd="32,0:3347,3449|36,0:1166,1263|40,0:2964,3001,3103|69,0:2502|82,0:5427,8892,28380,28489,28654"/><wd nm="ttempted" rd="38,0:2672,3849|40,0:1581|79,0:19284"/><wd nm="ttempting" rd="62,0:648"/><wd nm="ttempts" rd="32,0:1442,3294,3314|36,0:1113,1133|40,0:2813,2833,2877|68,0:4485,4655,4719|69,0:2458|79,0:19211|82,0:8849"/><wd nm="tten" rd="17,0:1949|21,0:3225|77,0:265,1199,1730,3822,5149,6271,7425,8852,9803,11156,12445,14390,15054,15897,16562,18151,19121,19707,20386,21337,22793,23249,24257,25660,27250,28635,29974,31012,32856,33727|79,0:264,1039,2474,4357,5530,7161,8615,10749,11678,13248,14032,15600,16994,18847,19989|80,0:156,1920|82,0:329,1092,1435,2769,3999,5081,6431,7626,9440,11114,12857,14522,16365,17599,19681,21249,22754,24141,25976,26988,28195"/><wd nm="ttend" rd="76,0:1425,3523"/><wd nm="ttendance" rd="35,0:629,1029,1274|38,0:1737|69,0:3735|73,0:967,1013|74,0:70,550|76,8:298,559|77,0:30103,30440|79,0:13431|82,0:10340,29041"/><wd nm="ttendant" rd="38,0:2754|40,0:1663"/><wd nm="ttention" rd="79,0:21153,21278,21440"/><wd nm="tter" rd="12,0:2978|16,0:1533,1559,1647,1741|17,0:1247|20,0:338,1484|24,137:0,23,446,483,505,540,568,585,909,962,1097,1195,1256,1276,1436|37,0:336,381|46,0:2957,2964|50,137:0,9,298,349,783,819,1034,1146,1236,1261,1278,1447,1921,1961,1985,2063,2177,2261,2304,2368,2429,2475,2511,2713|69,0:3308,3365|77,0:822,1046,7158,11808,11834,11922,12016,18865,20450,20501,21173,21966,25162,25188,25272,25322,25352,25389,25456|79,0:4942,8096,10555,18009|82,0:9915,9972"/><wd nm="tter&apos;s" rd="50,0:853,2236"/><wd nm="ttern" rd="78,0:3256,3532,3877"/><wd nm="tternenterthedesiredroutepatternprefixfollowedbyaperiodfollowedbytenxs" rd="78,0:3558"/><wd nm="tternforeachcalleridvaluethatyouwishtobeabletoset" rd="78,0:723"/><wd nm="tternontheciscocallmanagerwouldneedtohaveanentrythatmappedtheroutepatternprefixtotheappropriatecalleridvalueforthecampus" rd="78,0:1597"/><wd nm="tternprefixbasedonthecalleridvaluesetforthecalljob" rd="78,0:4588"/><wd nm="tternprefixesandtheircorrespondingcallidvaluestoyoursupportservicestechnician" rd="78,0:4858"/><wd nm="tternprefixestobeused" rd="78,0:1867"/><wd nm="tternprefixfollowedbyaperiodfollowedbytenxs" rd="78,0:3558"/><wd nm="tternprefixisastringofdigitsthatschoolmessengerwillprependtothephonenumberwhichwillthenbeusedbycallmanagertoidentifywhichcalleridtoassigntothecall" rd="78,0:1013"/><wd nm="tternprefixrecipient" rd="78,0:1344"/><wd nm="tternprefixtotheappropriatecalleridvalueforthecampus" rd="78,0:1597"/><wd nm="tterns" rd="78,0:4257"/><wd nm="tters" rd="13,0:1854|53,0:324"/><wd nm="ttes" rd="51,0:1858"/><wd nm="ttheappropriateciscocallmanagergroup" rd="78,0:2453"/><wd nm="ttheappropriatenumberingplan" rd="78,0:3723"/><wd nm="ttheappropriateroutefilter" rd="78,0:3758"/><wd nm="tthepartitionthatmatchesyourconfiguredctiportsforschoolmessengercommsuite" rd="78,0:3643"/><wd nm="ttheroutelistcreatedaboveforgatewayorroutelist" rd="78,0:3824"/><wd nm="tthevariousphonenumbersassociatedwiththecampusesinyourdistrict" rd="78,0:817"/><wd nm="tting" rd="6,0:55|8,0:593|10,1:9,453,484|13,8:332|15,1:13|16,8:289|17,0:2406|22,0:276|25,0:461|42,4:215,433|44,129:5,15,138|53,0:1553|56,0:698|61,0:1490,1538|62,129:0,27,2266|66,0:2037|68,0:5245|75,0:837,878|77,0:1882,2113,2346,4082,9879,13116,23433,26837|79,0:18,139,364,384,914,2349,2520,3246,4232,5405,5661,7036,8490,10624,11553,13123,13907,15475,16869,18722,19864|80,0:3209|82,0:1834,2347,3057,15094,16160,16882,25662,28421"/><wd nm="tting_Started.pdf" rd="79,128:21787"/><wd nm="tting_started" rd="79,0:0"/><wd nm="ttings" rd="2,0:358|4,0:667|16,0:1245|35,0:1089,1553|42,0:471|49,0:290,331,1538,2578|50,0:635,2222|56,4:2513,3329,6801|59,0:320|60,0:387,408,448,2212|61,8:567,588,609,639,670,698,761,788|62,0:923,969,1043|65,0:182,248,412,429,692,733,772|66,12:166,240,465,480,497,556,684,702,1059,1070,1081,1091|67,0:431,452|68,8:160,244,308,498,542,559,576,631,750,817,1005,1040,4864,4879,4894|69,0:6182,6227|77,0:11377,24657,26886,32388|79,0:800,856,3164,12612,17070,17413,19539,19636|80,0:302|82,0:1258,3124,6827,13173,13218,13765,17353,23609,27183,29081,29171"/><wd nm="ttitude" rd="1,0:600"/><wd nm="ttle" rd="10,8:423|51,0:1727|79,0:5328"/><wd nm="ttocallmanagerlincolnhighschool" rd="78,0:1418"/><wd nm="ttochangewithoutnotice" rd="78,0:227,2292,2721,3066,3474,4209,4540"/><wd nm="ttom" rd="12,0:1189,3551|17,0:1462|20,0:1640|21,0:2180|51,0:1112|53,0:1639|62,0:1159|77,0:4851,7879,9480,14773,19224,22076|80,0:1412"/><wd nm="tton" rd="0,0:1265,1328,1479,2064|1,0:1302,1845|2,0:691,710,1525|3,0:1321|4,0:961,1036|8,0:820,865,889,924,2490,3042,3694|9,0:324|10,0:1154|12,0:811,1178,1542,1771,1877,2077,2304,2467,3062,3334,3540|13,0:1014|15,0:762,807,1346,1391|21,0:4422|26,0:948,1261|28,0:413|29,0:225|31,0:451|33,0:822,928,1493,1628,3745|35,0:391|42,0:648,1504,1621,2077,2176,2353|43,0:431|47,0:841|48,0:673|49,0:1731,2426,2793,2877|50,0:826,1383,2070,2436,2518|51,0:882,1030,1101,2857,2863,2989,3088,3958,4004,4153|53,0:942,982,1364,1628,1751,1757|55,0:677|56,0:1416,2398,3205,6691,6773|58,0:413|60,0:1322,1477,2181|62,0:1148|63,0:844|64,0:906|65,0:970,1233,1492|66,0:2238,2427|67,0:582,976,1101|69,0:691,862,1069|70,0:604,3613|72,0:1078|77,0:3102,3254,3961,4557,4655,4840,5497,5738,5844,5884,6111,6460,6622,7204,7662,7868,8043,8502,9141,9211,10976,17238,22893,23473,23560,24851,25359,27057,27612,27729,27989,28088,28265,29425,29770,31441,33334|78,0:2805|79,0:2871,3187,3753,5703,5900,7281,7916,8215,9541,10813|80,0:1401,1582,1999|82,0:5633,6149,7274,13964,21434,21538,22816,22912,22972,23363,23537"/><wd nm="ttons" rd="32,0:2711|36,0:533|40,0:2234|49,0:2275|50,0:468|79,0:7501"/><wd nm="ttp" rd="46,0:3904"/><wd nm="ttributes" rd="82,0:18237"/><wd nm="tual" rd="3,0:1805|8,0:1493|20,0:236|47,0:178|77,0:21071|79,0:7602"/><wd nm="tually" rd="7,0:124|20,0:191|32,0:1774|47,0:133|77,0:21026,23369,25882"/><wd nm="tuation" rd="3,0:1711|21,0:2808|77,0:15542"/><wd nm="tuations" rd="17,0:1558|21,0:2276|77,0:14869,19320,26010"/><wd nm="tude" rd="1,0:600"/><wd nm="tudent" rd="1,0:749,870,994,1557,1578|11,4:1042|31,0:326|46,0:974|56,0:6218,6294,7094,7107|68,0:3963|70,0:2733,2858|72,0:555|76,0:3389,4347|79,0:706,13398,13493,15186,16072|80,0:2966|82,0:15590,15715,23900,23913,28704,28775"/><wd nm="tudent&apos;s" rd="1,0:305,701|76,0:4279"/><wd nm="tudents" rd="1,0:1381,1490|11,0:1081,1315,1697,1897,1930,2280|56,0:2635,2740,2769,2941|59,0:687|68,0:3771,3937|72,0:388,615,833|75,0:94|76,0:1050,1138,1850|79,0:15224,15411,16406"/><wd nm="tudent’s" rd="46,0:3753"/><wd nm="tudy" rd="76,0:2005,2073,2156"/><wd nm="tuesday" rd="76,0:1085,1275,1694,3171,3702"/><wd nm="tuguese" rd="3,0:813"/><wd nm="tulations" rd="80,0:2699"/><wd nm="tulatory" rd="74,0:703"/><wd nm="tunities" rd="77,0:26560"/><wd nm="tunity" rd="76,0:3286,3924"/><wd nm="tup" rd="25,0:355|80,0:363"/><wd nm="turally" rd="6,0:252"/><wd nm="turday" rd="76,0:2675,3015"/><wd nm="ture" rd="1,0:77,138,193|2,0:75,136,191|3,0:79,140,195,1778|4,0:63,124,179|5,0:87,148,203|7,0:61,739,981,1061|8,0:2772,3163|12,0:1126|13,0:1447|14,0:817|16,0:272|18,0:217,271,292,400|19,0:1283|20,0:997|24,0:215,269,290,398|26,0:221,313|27,0:92,193,334,1024|33,0:1018,2324,2803,3414|34,0:77|42,0:98|45,0:420|46,0:1805|47,0:240|48,0:47,101,122,230,333|50,0:45,99,123,254|51,0:227|56,0:6823|59,0:795|60,0:35,315|61,129:24,57,93,146,258,304,398,1759|62,0:81,134,246|66,0:233,1192,1988,3128|68,0:237|69,0:2189,2952|70,0:2091|72,0:218|74,0:853|75,0:1252|77,0:1978,4993,18466,21567,25970,29246,31131|78,0:544|79,0:1409,3863,6663,14979,17651|80,0:3185|82,0:1801,3839,8582,9559,14988,21713,23631"/><wd nm="tures" rd="2,0:413,1228|4,0:722|8,0:546|10,0:1910|11,0:84,154|12,0:78,148|13,0:58,128|14,0:63,133,356,1214|15,0:61,131|16,0:2032,2235|17,0:298|18,0:80,150|19,0:74,144,512,1690,2023|20,0:72,142,442|21,0:301,1332,1420,1543|22,0:64,134|24,0:78,148|25,0:168,256,636|26,0:90,160|30,0:78,148|34,0:315,385|39,0:62,132,1360|41,0:68,138|42,0:522|43,0:732,836|46,0:332,632|47,0:1093|48,0:921,1025|49,0:62,132|50,0:1630,1734|51,0:100,170|52,0:82,152|53,0:78,148|54,0:98,168|55,0:64,134|56,0:273,343|57,0:84,154|60,0:1219|65,0:70,140|66,0:54,124|68,0:48,118|69,0:80,150,265|70,0:76,146|71,0:79|77,0:1861,1936,2015,2146,2202,3502,4280,4457,10068,10231,10584,13354,13455,13602,26931|79,0:1446,1579,8185,12520|82,0:1149,1591,1736,1749,2567,2597,3074,6538,6704,17294,21010,27046,27084,27124,27319,27401,27434"/><wd nm="turn" rd="15,0:1042,1598|17,0:2095|20,0:2119|21,0:3371,5106|38,0:3107|40,0:2016|50,0:953|58,0:832|72,0:233|77,0:8924,9347,16043,17990,19853,25488|79,0:3477,8685,11773|82,0:22824,23576,28910"/><wd nm="turned" rd="12,0:3581|35,0:1474|77,0:7909|79,0:12029"/><wd nm="tus" rd="9,0:135|32,0:1759|38,0:1956|40,0:1453,1502|49,0:1034|56,0:1930|60,4:601,611,712,727|71,0:755,1719"/><wd nm="tute" rd="79,0:14593"/><wd nm="tutorial" rd="11,0:252|12,0:473|15,0:230|17,0:451|18,0:628|20,0:561|21,0:492|22,0:366|23,0:482|24,0:615|77,0:13103,25908|79,0:5785,14507"/><wd nm="tware" rd="7,0:378|42,0:1433|77,0:8160,26081,26216"/><wd nm="twaremustalsobeconfiguredtoassigntheappropriateroutepatternprefixbasedonthecalleridvaluesetforthecalljob" rd="78,0:4588"/><wd nm="tween" rd="21,0:3831|67,0:333|74,0:134|77,0:16867,25382|79,0:10114"/><wd nm="twelve" rd="76,0:1935"/><wd nm="twillbesenttocallmanagerlincolnhighschool" rd="78,0:1418"/><wd nm="twitter" rd="16,0:1533,1559,1647,1741|20,0:338|24,9:0,23,446,483,505,540,568,585,909,962,1097,1195,1256,1276|37,0:336,381|50,9:0,9,298,349,783,819,1034,1146,1236,1261,1278,1447,1921,1961,1985,2063,2177,2261,2304,2368,2429,2475,2511|69,0:3308,3365|77,0:822,1046,11808,11834,11922,12016,20450,20501,21173,25162,25188,25272,25322,25352,25389,25456|79,0:4942,8096|82,0:9915,9972"/></pk>