<?xml version="1.0" encoding="UTF-8" standalone="no"?>
<pk><wd nm="atabase" rd="10,0:374,1705|14,0:329,1660|16,0:3733|18,0:2830|31,0:3734,3843,3983,4036,4092,4176,4236,4316,4392,4475,5441,5594,5791,6786,6859|35,0:177|36,0:499|37,0:345,607|44,0:1884,2708|45,0:6443|46,0:3166|48,129:10,38,57,136,498,682,707,745,1184,1515|49,0:423|53,0:4250,6508"/><wd nm="atabovestepsforadditionalcalleridnumbersandroutepatterns" rd="54,0:4257"/><wd nm="ataor" rd="53,0:6055"/><wd nm="atappearsonarecipient" rd="54,0:275"/><wd nm="atcampus" rd="54,0:924"/><wd nm="atch" rd="35,0:1442,1648,1687,1916|53,0:6529"/><wd nm="atchesyourconfiguredctiportsforschoolmessengercommsuite" rd="54,0:3643"/><wd nm="atconfigurationisdonebytheschoolmessengersupportservicestechnicianassignedtoyouraccount" rd="54,0:4769"/><wd nm="ate" rd="0,0:385,459,579,1147,1761,3449|2,0:92,875|5,0:190,315,441,1103,1301|6,129:8,48,841,1785|7,129:8,50,431,1375|9,0:144|10,0:1008,1016,1055,1063|11,0:236,337,488,531,561,929,1007,1457,1531,1750,1865,1900,2154,2230,2634,2708,3292|12,0:94,207,484,515|13,0:319,1047,1328|14,0:963,971,1010,1018|15,0:124|16,0:920,1982,1996,2035,2049,3267,3302,3372,3451|18,0:112,2133,2141,2180,2188|20,0:411,660,1037,1349,1390,1646,1996,2190,2345|21,0:72,166,445,576,653,742,758,1402,1606|23,0:1225|24,0:324,648,850,1899,2190|25,0:147,174,258,280,305,354,448,538,554,1011,1025|26,0:713,948,1052,1141,1157,1568,1757,1950|27,0:1036,1343,1937|28,0:1042,1372,1607,1712,1802,1818,2230,2417,2609,2844|29,0:493,960|30,0:545,618|31,0:740,1833,1840,2015,2053,2067,3536,3661,3680,3907,3914,3929,4123,4130,4913,4932,6039,6196,6248,6966,7001,7127,7146|32,0:396,1070|33,0:342|35,0:693|37,0:948,1840|40,0:833,858,885,1462,2393,2422|42,0:2023,2047,2079|43,0:66,389,1158|44,0:2360,2730,2759,2777,3190,3291,3428,3519|45,0:364,676,2345,2939,3355,3464,3604,3652,3688,3715,3907,3947,4067,4507,4676,4756,4807,5089,6035,6110,6328,6527|46,0:294|47,0:1557,1580,1714,1729,1855|48,0:571|51,0:362|52,0:1226,2202|53,0:938,947,1847,2265,2513,2617,4699,4779,5394,5891,6395,7171,7303,7503,7687,7728,8270,8505,8564,8735,8770,9349,9409,9462,10115,10674,10793,11922,12112,13222,13692,14954,16787,17651,18263,19213,19327,19352,19563,19599,19867,20250,20259,20342,22203,22256,23157,23395|55,0:860,879,3335,3416,4399,4505,4563,4573,4748,4930,5040,5123,5204,6521,7319,7372,9444,9678,10959,11012,11706,12251,14098,15443,17781,19435,19712|56,0:429,1366,1545"/><wd nm="ateacallroutelistandroutepatternforeachcalleridvaluethatyouwishtobeabletoset" rd="54,0:723"/><wd nm="atecalleridvalueforthecampus" rd="54,0:1597"/><wd nm="ateciscocallmanagergroup" rd="54,0:2453"/><wd nm="ated" rd="0,0:535,1110,1369,1885|3,0:24|4,0:349,478,682,1077|6,0:929|7,0:518|10,0:909,1288,1347,1401,1590,1643|14,0:864,1243,1302,1356,1545,1598|16,0:1192,1244,1260,2859|17,0:502,517,856,1390,1507|18,0:235,1094,2034,2413,2472,2526,2715,2768|23,0:1149,1311|25,0:1214,1791,2207,2303,2566|28,0:2632|31,0:756,3060,3398,3863,3898,4530,4710,4855,5315,5480|34,0:475,569|37,0:1786|40,0:1610,2209|42,0:1869|43,0:743|44,0:3249|45,0:4037|46,0:2245,2659,2986,3083|47,0:2026|53,0:1663,3461,4337,4818,4927,5929,7423,10161,12292,12973,14679,15105,15657,16556,16819,16961,20747,20944,21104,23429|55,0:637,959,1593,3629,7520,8583,9993,10268,10347,10449,11982,12355,13257,13331,14329,14803,14815,15675,16337,20371,20409,20426|56,0:1054,2271,2376,3344,3709"/><wd nm="atedaboveforgatewayorroutelist" rd="54,0:3824"/><wd nm="atedwiththecampusesinyourdistrict" rd="54,0:817"/><wd nm="ategies" rd="51,0:218"/><wd nm="ategories" rd="20,0:256,271,397,438,462,625,1454|45,0:6545"/><wd nm="ategory" rd="20,0:508,595,951,997,2161|21,0:527|55,0:9124"/><wd nm="ately" rd="0,0:3150|27,0:1436|28,0:559|51,0:1149|52,0:2290|53,0:17072,17758|55,0:11106,13464|56,0:2964"/><wd nm="atemlppprecedence" rd="54,0:3791"/><wd nm="atenumberingplan" rd="54,0:3723"/><wd nm="ater" rd="11,0:2097,2577,3132|20,0:343|24,0:3946|29,0:938|32,0:202|44,0:4201|53,0:1552,7626,17128|55,0:1497,4991,11162,13520"/><wd nm="aterials" rd="53,0:219,1140,2727,3820,5297,7060,8395,9770,11148,12805,14081,14863,16213,16669,17350,18966,20134,22038,22909"/><wd nm="ateroutefilter" rd="54,0:3758"/><wd nm="ateroutegroup" rd="54,0:2833"/><wd nm="ateroutepatternprefixbasedonthecalleridvaluesetforthecalljob" rd="54,0:4588"/><wd nm="ates" rd="23,0:460,1427,1630,1818,1988,2175|24,0:2280,3585|50,0:312|51,0:947|52,129:7,29,4512|53,0:8818,22186"/><wd nm="atest" rd="2,0:1286|31,0:5456|45,0:2669|55,0:18132"/><wd nm="atewayorroutelist" rd="54,0:3824"/><wd nm="ath" rd="52,0:2225|55,0:19859"/><wd nm="ather" rd="30,0:202|51,0:547|53,0:14627"/><wd nm="athletic" rd="50,0:824"/><wd nm="atic" rd="24,0:1121|31,0:6430,6819|53,0:10718,11847"/><wd nm="atically" rd="0,0:1872|13,0:97|23,0:181,1212,1298|24,0:1447,1819|25,0:205,1778|28,0:2564|31,0:5200,5405,6971,7030|44,0:3236|53,0:9396,10102,10780,11510,11909,12099,13209,14705,19169,19801|55,0:4579,4835,9586,9895,9980,10813,11684,15745|56,0:1096,2734,3331"/><wd nm="ating" rd="0,0:346,2489,3418|1,0:406|3,0:701,717|11,0:1079,1120|12,0:849,958|13,0:539,565|20,16:915,1146,1184,1201,1242,1692|21,8:188,244,285,329,605,964,1051,1254,1287,1531|23,0:57|25,129:0,13,801,958,1712,2584,3118|26,0:1363,1450,1608,1641|27,0:855|28,0:2026,2113,2269,2302|29,129:16,57,1786|30,0:295,368,392,485,516|31,0:655,2728,3619,4864,5163,5504|35,0:213|40,0:1753,2580,3259,3527,3791|41,0:954,1218,1478|42,0:502,530,614,643,671,693,773,815,1416,2119,2138,2257|43,0:355|44,0:1827,2172,2400,2481|45,0:414,3610,3658,5372,5415|46,0:2837|47,0:316,337,2176,2203,2248,2340|53,0:486,710,743,888,897,961,4757,7449,7651,7956,9230,14170,14366,17979,19055,19064,19256,19287,19334,19489,19605,22127|55,0:318,4967,5151,7238,8222,8752"/><wd nm="atio" rd="44,0:4630"/><wd nm="ation" rd="0,0:1337,1784,2445|2,0:409,484,584,648,666|3,0:661|4,0:978|5,0:483|6,0:1463|7,0:1052|10,0:48,857,1896|11,0:243,360,415,441,685,711|12,0:180,530|14,0:44,812,1856|15,0:83|16,129:0,31,54,161,262,351,512,666,700,749,795,1012,1035,1171,1204,1223,1511,3914,4228|17,0:696,759,780,917,1322,1434|18,0:739,1982|20,0:114|21,0:1428|24,0:145,871,979,1249,1695,2645,2890,3138,3172,3431,3765|25,0:54,1440,1536|26,0:218,1783|27,0:2442|28,0:216,892,2443,3062,3124|29,0:912|30,0:208|31,0:975,2839,3694,3885,3943,4427,4805,5222|32,0:218,405|33,129:0,22,45,976|34,0:175,263,335,376,398,550,873,886,951,978,1001,1055,1084,1105,1165|36,0:261,517|37,0:249|40,0:229,285,352,443,916,1599,1915,2068,2682,2851,2917,2986,3278,3300,3546,3568,3808,3828|41,129:0,17,227,291,316,442,492,561,973,995,1237,1259,1495,1515,1671|42,0:199,263,288,1576,1728,2357|44,0:205,269,294,559,587,1088,1111,1139,1371,3475|45,0:260,976,1728,1768,1848,3779,5036,5465,5675|46,0:1664,1814,1843,2687,2737,3025|47,0:578,871,1412,2382|48,0:538,1356|49,0:97,275,299,328,385,554,685,898|50,129:0,18,119,481,671,740,1150|51,0:45,205,585,737,854,930,1049,1523,1689|52,0:887,914,1697|53,0:1366,1927,2417,2495,2577,2846,3077,3622,6089,6247,6555,10000,10198,10309,10727,11856,12500,12594,13312,13384,13495,15313,15407,17184,19152,20348,20869,21239,21524,21650,21727,22596,22659|54,0:4975|55,0:447,607,714,727,847,1722,3355,3433,3882,3982,4169,6342,7580,7622,8209,8358,8506,8761,8789,8820,9413,9707,10171,10219,11219,11874,11946,12595,12771,12831,13117,13177,13577,14037,14112,14152,14652,14702,15099,15273,15488,15905,16476,16520,17884,19243,19307,19424,20148|56,0:942,965,1246,3027,3208,3651"/><wd nm="ational" rd="34,0:814"/><wd nm="ationisdonebytheschoolmessengersupportservicestechnicianassignedtoyouraccount" rd="54,0:4769"/><wd nm="ationisrequiredinordertoutilizethisfeature" rd="54,0:544"/><wd nm="ationjobfromlincolnelementaryschoolwoulddisplaythecalleridforthatcampus" rd="54,0:924"/><wd nm="ations" rd="0,0:358,3494|1,0:1039|2,0:1542|3,0:411,958|4,0:1505|5,0:1433|6,0:1659|7,0:1249|8,0:603|9,0:524|10,0:2199|11,0:3789|12,0:245,1239|13,0:823,1407|14,0:2162|15,0:494|16,0:4110|17,0:1916|18,0:3693|19,0:522|20,0:1359,2396|21,0:693,1654|24,0:368|25,0:488,3000|26,0:1092,1999|27,0:2900|28,0:1752,3516|29,0:1652|30,0:789|31,0:7337|33,0:298,858|34,129:8,29,49,432,497,597,1118,1208,1334|38,0:954|39,0:975|41,0:1553|42,0:2541|43,0:1300|44,0:4817|45,0:3004,5822,5854,5951,6576|46,0:3057,3282|47,0:2766|48,0:1387|49,0:1104|50,0:566,586,785,1032|51,0:1767|52,0:2823,4109,4387|53,0:44,168,290,1089,1211,1678,1773,2676,2798,3769,3891,5246,5368,7009,7131,7697,8344,8466,9719,9841,11096,11219,12753,12876,13268,14029,14152,14811,14934,16161,16284,16617,16740,17298,17421,18914,19037,19450,19573,20082,20205,21451,21986,22109,22857,22980|54,0:83,136,2148,2201,2577,2630,2922,2975,3330,3383,4065,4118,4396,4449|55,0:40,170,1022,1329,2041,2602,3542,3718,4103,5176,5412,6061,6426,6727,7064,7105,7344,7885,7954,9039,10544,11498,12428,12671,13012,14454,15378,16056,16878,18260,18878|56,0:76,243,328,566,1520,2045,2608,3172"/><wd nm="ations1" rd="53,0:19311"/><wd nm="ationsaresubjecttochangewithoutnotice" rd="54,0:227,2292,2721,3066,3474,4209,4540"/><wd nm="ationships" rd="55,0:19008"/><wd nm="ationsselectpredotfordiscarddigits" rd="54,0:3931"/><wd nm="atistics" rd="19,0:188,296,465,486|45,0:1925"/><wd nm="ative" rd="27,0:429|50,0:539|52,0:564"/><wd nm="atively" rd="26,0:897|28,0:1556|53,0:16435"/><wd nm="atmappedtheroutepatternprefixtotheappropriatecalleridvalueforthecampus" rd="54,0:1597"/><wd nm="atmatchesyourconfiguredctiportsforschoolmessengercommsuite" rd="54,0:3643"/><wd nm="atneededtobeconfigured" rd="54,0:1796"/><wd nm="ator" rd="0,0:2966|3,0:284|4,0:181|5,0:73|8,0:181|12,0:404|16,0:3252|17,0:163|18,0:1492|19,0:169|26,0:451|27,0:153|29,0:199|30,0:165|31,0:372,6050,6142,6252,6722|40,0:157|41,0:161|42,0:133|44,0:139|45,0:181,223,349,5973|46,0:177,278|48,0:440|53,0:5070,19709,21497|55,0:1946,2689,5759,6164,6843,9388,12146,18558"/><wd nm="atorinterface" rd="54,0:2038"/><wd nm="ators" rd="27,0:194,209"/><wd nm="atory" rd="24,0:259|50,0:716"/><wd nm="ats" rd="12,0:1125|19,129:5,31,346,645|31,0:7150|36,0:1357|45,0:5127,5167|53,0:6040"/><wd nm="atschoolmessengerwillprependtothephonenumberwhichwillthenbeusedbycallmanagertoidentifywhichcalleridtoassigntothecall" rd="54,0:1013"/><wd nm="attach" rd="21,0:1204|25,0:1982|53,0:15577"/><wd nm="attached" rd="21,0:1362|26,0:1716|28,0:2377,2577"/><wd nm="attachments" rd="25,0:1832,1934|53,0:15532,15763"/><wd nm="atted" rd="35,0:1414|53,0:8517"/></pk>