<?xml version="1.0" encoding="UTF-8" standalone="no"?>
<pk><wd nm="eck" rd="5,0:1292,1354|12,0:1899,2040,2135|13,0:125|16,0:1358|27,0:233|41,0:770|43,0:445,1723|46,0:762|57,0:4175|67,0:5350|72,0:1159|74,0:1129,1152|75,0:1189,1212|77,0:2045,2686,2707,2871|78,0:519,921|80,0:1500,1602,1710,1852,1948,2282,2393,2622,2760,3617,4118,4460,5751,5826,5909|83,0:515|88,0:5316|90,0:2937,10934,19759|91,0:2747,2764|93,0:5797,7946,8048,8156,8306,8423,8509,8621,8973,9084,9511,9649,10502,11199,11539,13024,13099,13182,28724"/><wd nm="eckbox" rd="5,0:1302|15,0:1208,1601,2061,2173|16,0:2548,3417|41,0:1397|65,0:1038|77,0:892,2152|78,0:544|84,0:1002|88,0:6703,7745|90,0:15304,16171,16291|93,0:5811"/><wd nm="eckboxes" rd="84,0:801|93,0:15392"/><wd nm="ecked" rd="16,0:1094|79,0:3378|84,0:1030,1066|88,0:4961"/><wd nm="ecking" rd="1,0:1435|2,0:1248|16,0:998,2537|46,0:3241|77,0:968|79,0:3201|84,0:848|88,0:4800,6692|93,0:20590"/><wd nm="eckmarks" rd="88,0:23976"/><wd nm="ecognize" rd="86,0:1157"/><wd nm="ecome" rd="10,0:577|50,0:929"/><wd nm="ecomes" rd="54,0:1083"/><wd nm="ecommend" rd="6,0:1730"/><wd nm="ecommended" rd="88,0:34020"/><wd nm="ecommunications" rd="89,0:83,136,2148,2201,2577,2630,2922,2975,3330,3383,4065,4118,4396,4449"/><wd nm="econd" rd="48,0:2954|82,0:2914|87,0:3999|90,0:15721"/><wd nm="econds" rd="46,0:2887,3045|48,0:1796,1954|90,0:21377"/><wd nm="econfigured" rd="89,0:1796"/><wd nm="econfiguredtoassigntheappropriateroutepatternprefixbasedonthecalleridvaluesetforthecalljob" rd="89,0:4588"/><wd nm="econfiguringcalleridwithciscocallmanagercopyright" rd="89,0:2086,2515,2860,3268,4003,4334"/><wd nm="econtactyourschoolmessengercustomersolutionsengineerforassistance" rd="89,0:5025"/><wd nm="ecord" rd="3,0:968,1171,1184|4,0:1759|12,0:2972,3373,3423,3497|20,0:1814|24,0:2373,2403|25,4:906,961,3789,4075,4131,4161,4202|35,0:139,281|36,0:237,323,509,565,625,774|37,0:321|65,0:322,442|67,0:7046,7176|68,0:1145,1229|77,0:1428,1528|80,0:1919|88,0:12089,13022,13057,16617,16672,16702,16743,16825,31161,31632|90,0:8239,8441,8771,8807,8858,9010,9109,9166,17572|91,0:1298,2020,2210,2495|93,0:8576,23852,23982"/><wd nm="ecorded" rd="4,0:293,656|25,0:432,1484,3593,4299,4522,4560|35,0:660|68,0:1019,1396|88,0:13518,16131,17115,17338,17376|91,0:2596,2837"/><wd nm="ecording" rd="4,0:1792|12,0:2740,3254,3395|25,0:997,1195,3938|35,0:257|36,0:192,425,455,633,678|37,0:196,237,267|80,0:1842|86,0:349,390,1348|88,0:13242,16968|90,0:8900,9425,18690,20305,20596,20987|91,0:1224,2311|93,0:8499"/><wd nm="ecordings" rd="25,0:3561|86,0:1280,1465|88,0:16331"/><wd nm="ecords" rd="67,0:1862,5291,7114|93,0:23920"/><wd nm="ecpients" rd="46,0:1520"/><wd nm="ecretary" rd="87,0:569,4461"/><wd nm="ect" rd="1,0:1366,1394,2220|2,0:1030,1135,1236,1734,1840,1958|3,0:631|5,0:981,1152|6,0:1103,1284|8,0:745|9,0:1119,1178|12,8:956,1070,1116,1186,1413,1716,1770,1874,2015,2112,3876|15,0:704,1163,1551,1883,2010,2028,2124|16,0:2505,3114,3175,3265|17,0:792|19,0:793,1377,1579|20,0:373|21,0:778,1407|25,0:913,1227,1837,2125,2325,4735,4898|30,0:1098,1508|31,0:410|32,0:1370|33,0:300|36,0:535,1056,1120,1423,1503|37,0:647,711,1023,1103|41,0:480,620,660,1168,1331,1704,1851,2039,2123,2402,2549,2602,2879,3010,3129,3159,3215,3520,3785,3854,3901|43,0:302,1115,1222,1265,1579,1683|46,0:599,902,2514,3023,3128|48,0:625,1932,2037|49,0:388|50,0:1055,1556|51,0:462,489,534|52,0:753|53,0:1010|54,0:650|57,0:3345|59,0:351,704,731|60,0:395,618,1714,2017,2058,2118,2404,2776,2860,2897|61,0:810,1096,1137,1196,1414,1441,2049,2420,2502,2538|62,0:952,1514,1566,1637,2998|64,0:1358|65,0:963|67,0:2528,5001,5514,6252,6347,6514,6672,7556|68,0:1314,1419|69,0:421,466,617,696,857|71,0:2228|72,0:954,1446|73,0:1197,1225,1352,1381,1876,1982|76,0:927,1190,1449|79,0:4936,5190|80,0:2032,2111,2185,2918,3109,3899,3987,4136,4839,4955,5042,5122,5223,5284,5974,6050,6144|81,0:2442,2506,3012,3056,3173,3322,3457,3491|83,0:905,941,995|86,0:1423|87,0:810|88,0:4428,6660,7256,7500,7593,8488,9328,10308,12947,14438,14718,15102,16402,17617,17780,18357,19169,23584,23680,23897,24100,24834,25343,27645,30348,30641,30719,31802,31915,31952,32226,32453,33481|90,0:455,2217,2973,5924,6016,6063,6193,6304,6364,6571,7256,8222,9678,9759,11241,11458,12880,14435,14712,14792,15036,15252,15271,15657,15681,15706,15740,15938,16119,16138,16257|91,0:823,1365,1674,1699,1727,2040|93,0:3375,4148,4261,5965,8705,8784,8858,9807,9998,10782,10870,11217,11914,12030,12117,12197,12298,12359,13247,13323,13417,14051,15245,15311,15893,19429,21441,21674,22921,23172,23235,24562,26038,26712,28628"/><wd nm="ectappropriatemlppprecedence" rd="89,0:3791"/><wd nm="ectappropriateroutegroup" rd="89,0:2833"/><wd nm="ected" rd="1,0:1474|10,0:1119|12,0:434|15,0:1326,1708,2291|16,0:3463|20,0:450|40,0:1147,1418|41,0:1990|43,0:1301,1490,1893|46,0:2559,2970,3064,3647,3711,3803|47,0:1628|48,0:670,1056,1324,1879,1973,3256|60,0:2090,2187|61,0:841,1168|63,0:586|65,0:683,1372|67,0:130,3632,5809,6062,6562|73,0:770,1405|79,0:1751|80,0:3282|88,0:7791,10403,25422,32132,32439|90,0:3020,7618,10175,12847,13669,15422,15857,16417|93,0:7177,10171,25510"/><wd nm="ecting" rd="1,8:1092,1566|6,0:757|12,0:1616,1667|16,0:1821|21,0:2030|25,0:1807,3306|32,0:1155,1358|36,0:812|37,0:404|41,0:2951,2979|47,0:409|60,8:1196|61,8:287|62,0:1129,1161,1876,1908|63,0:388|64,8:617,1198|73,0:2044,2086|78,0:1009|88,0:5788,15978,19788,23779,31670|93,0:3625"/><wd nm="ection" rd="0,0:1032,1913,2504|3,0:421,903|5,0:730,762|7,0:154,616|8,0:172,641|9,0:160|10,8:830|12,0:2949,4076|13,0:637,723,891|14,0:50,1799|16,0:299,363,408,837,1410,1808,2341,3099|17,0:417,1196|18,0:1163|20,0:1961,2164|21,0:563|22,0:740|23,0:1639,1952|24,0:673,1789|25,0:604,1661,2889,3896,4828|26,0:478|27,0:594|28,0:727|32,0:273|33,0:554|39,0:221,425|40,0:25,248,2181|41,0:2067,2115,2203,2682,3293,3824,3967|43,0:1675,1925|44,0:21|46,0:1176,1626,2252|47,0:541,1080,1353,1532,1560,1717|48,0:254|50,0:530,1119,1243,2067|54,0:893|58,0:998|60,0:2141|61,0:1219|64,0:777|67,0:1501,5631,6648|71,0:495,1025,1573|76,0:472|77,0:448,526|79,8:296,608,934,3713|81,0:480,1145,1181,1468,1692,2831,3065|82,0:193,264,330|84,0:682|86,0:135|88,0:2071,2263,2970,3481,4317,5368,5775,6497,7241,9653,10098,13680,13886,15623,16932,17710,22225,23890,26939,27960,30575,32955,33570|90,0:1502,2583,4167,4419,11748,11880,12578,12635,12911,12977,13758,13835,14319,14630,17693,21070|91,0:1139,3251|93,0:1906,2381,2988,3088,3132,3157,4660,4752,6495,6647,6745,7835,8467,14017,14138,15688,16073,17317,17361,17386,18763,18917,21033,21075,21305,27147,27191,27216"/><wd nm="ections" rd="13,0:274|15,0:967|17,0:1158|36,0:1567|37,0:1167|40,0:2878|44,0:701|46,0:1020|48,0:2401|62,0:3734|67,0:1054|80,0:1440|81,0:2909,2955,3094,3280|88,0:4258,32574,33306|90,0:5736,12400,15101"/><wd nm="ective" rd="57,0:72|78,0:86|85,0:61|86,8:303,1309|90,0:11034,20089"/><wd nm="ectively" rd="14,0:919"/><wd nm="ectly" rd="6,0:1779|13,0:706|14,0:1551|21,0:1157|24,0:1394|25,0:2718|88,0:2909,3196,15479,18775,21876|90,0:10465|93,0:25032"/><wd nm="ectlymodifythecalleridvalue" rd="89,0:690"/><wd nm="ectpredotfordiscarddigits" rd="89,0:3172,3931"/><wd nm="ectprovideoutsidedialtone" rd="89,0:3901"/><wd nm="ectroutethispattern" rd="89,0:3877"/><wd nm="ects" rd="1,0:394|6,0:607|12,0:1273|60,0:2436|61,0:2080|87,0:3338"/><wd nm="ecttheappropriateciscocallmanagergroup" rd="89,0:2453"/><wd nm="ecttheappropriatenumberingplan" rd="89,0:3723"/><wd nm="ecttheappropriateroutefilter" rd="89,0:3758"/><wd nm="ectthepartitionthatmatchesyourconfiguredctiportsforschoolmessengercommsuite" rd="89,0:3643"/><wd nm="ecttheroutelistcreatedaboveforgatewayorroutelist" rd="89,0:3824"/><wd nm="ecttochangewithoutnotice" rd="89,0:227,2292,2721,3066,3474,4209,4540"/><wd nm="ecure" rd="52,129:5,34,565,1815|53,0:392,430,861|54,0:292"/><wd nm="ecurity" rd="79,8:997,1014,4234,4246,4263|80,4:385,5706|90,0:9968|93,0:1204,2091,12980,27944,27955,28020"/><wd nm="ecutive" rd="87,0:1217"/><wd nm="ed" rd="0,0:520,832,1130,1164,1221,1334,1429,2016,2186,2216,2462,2515|1,0:616,652,756,1008,1253,1474,1501,1624,1730,1894,2245,2398,2466|2,0:354,449,592,735,1335,1383,1657,2067|3,0:345,512,1070,1220,1319,1398,1433,1471|4,8:293,454,522,541,656,1429,1692|5,0:310,337,547,654,1085|6,0:270,485,549,696,725,1221,1575,1651,1788|7,0:101,364,411,636|8,0:119,276,363,399,425,471,532,571,610,656,806,833|9,0:107,386,517,711,720,730,761,830,841,1128,1190|10,0:339,356,367,409,488,551,1119,1200,1296,1559|11,0:359,386,502,645,746,1008|12,0:105,216,244,336,352,434,472,508,538,600,613,650,741,826,876,1298,1442,1544,1799,1955,2159,2249,2311,2680,2695,2814,2841,3283,3364,3466,3526,4095|13,0:254,683,972|14,9:16,153,284,333,460,491,535,712,736,819,1338,1349,1476,1560,1902|15,0:107,757,1225,1326,1433,1708,1815,2190,2291,2398|16,0:101,237,258,607,678,953,962,1094,1326,1694,1777,2310,2731,2789,2827,3068,3463,3490,3519,3581|17,8:81,339,462,1036,1137,1328,1517,1674,1779|18,8:86,336,935,1189,1245,1309|19,1:20,84,442,813,1288,1397|20,8:221,296,450,603,1028,1101,1510,1602,1775,1858,2227|21,8:276,331,412,946,1061,1070,1301,1320,1737,1753,1771,1828|22,0:103,464,476|23,8:97,356,504,767,1401,1665,1721,1791,1825,2015|24,8:95,276,315,432,511,1015,1102,1114,1183,1298,1307,1743,1875,1922,1969,2060,2233,2307,2538|25,0:279,432,880,1262,1484,1604,1727,1781,1883,2039,2472,2495,3013,3029,3047,3104,3503,3593,3667,3905,4042,4087,4299,4522,4560|26,137:3,19,87,194,325,339,660,729,751,768,846,980,994,1079,1141,1164,1318|28,0:101,461,473,1083,1138,1173|29,0:26,468,499,578,628,909,1107|30,0:113,322,353,373,399,422,482,544,662,686,1049,1114,1445|31,0:85,584,737,747|32,0:103,249,280,378,417,456,649,796,866,1075,1110,1307,1408|33,0:96,250,737,765,885,1193,1273,1304,1339,1588,1632|34,0:81,260,434,471|35,0:81,379,451,528,660|36,0:395,500,732,901,914,930,998,1300|37,0:312,492,505,521,589,895|38,0:101|39,0:90|40,0:220,495,600,617,805,821,897,1002,1147,1188,1258,1418,1431,1486,1686,1796,1822,2006,2057,2104,2265,2291,2299,2325,2334,2381,2408,2438,2480,2673,2846,2930,2945,2967,2988,3163,3270,3379,3466,3639,3700|41,0:62,148,158,761,782,1412,1466,1589,1962,1981,1990,3894|42,0:33,131,338,593,671,776|43,8:78,618,1014,1145,1301,1474,1490,1893|44,0:495,669,747,762,784,799,974,1089,1198,1280|45,0:72,440|46,12:103,298,394,540,773,784,804,1004,1028,1065,1135,1148,1164,1293,1532,1772,1816,1884,1946,2011,2134,2214,2332,2353,2372,2431,2497,2559,2672,2724,2733,2745,2819,2929,2970,3064,3360,3400,3419,3446,3469,3540,3647,3711,3803,3849,3882,3916,3947,3983,4010|47,8:85,274,326,374,514,529,658,869,994,1014,1403,1439,1477,1520,1628,1673,1847|48,0:66,227,443,464,483,542,608,670,751,929,1032,1056,1096,1165,1324,1358,1409,1430,1485,1581,1633,1642,1654,1728,1780,1838,1879,1973,2196,2369,2453,2468,2490,2511,2686,2789,2885,2936,3033,3120,3256,3305,3361,3393|49,0:91|50,137:18,42,76,94,160,231,289,341,396,417,479,503,788,877,912,955,1002,1033,1080,1092,1192,1224,1334,1387,1422,1509,1581,1672,1691,1700,1783,1850,1901,1910,1949,1966,1988,2011,2258,2290,2324,2500,2618,2654,2846|51,141:14,34,152,174,298,322,661,724,768,881,890,976,991,1026,1197|52,0:118,267,532,542,859,924,998,1030,1086,1138,1210,1283,1582|53,0:93,289,357,532,604,677,802,1227|54,0:97,246,366,409,615,961,1031|56,8:308,455,727,1111,1160,1321,1343,1574,2125|57,0:314,557,640,818,1109,1157,2072,2141,2228,2298,2860,2977,3141,3359,4129|58,0:75,218,325,539,661,689,733,951,1076,1165,1306|59,4:484,850,913,957,1070,1079,1165,1180|60,0:85,359,381,519,554,691,722,896,1238,1411,1752,1777,1793,1822,1943,2090,2187,2516,2755,2818|61,4:320,508,841,1023,1168,1559,1622,1666,1779,1788,1874,1889,2160,2399,2461|62,0:123,334,343,522,557,571,585,830,1061,1722,1971,2094,2347,2901,3036,3170,3348,3378,3408,3486,3531,3677,4205,4233|63,0:105,274,359,586,689,726,888,954,1041|64,0:101,485,567,909,1121,1151|65,0:121,432,683,889,1252,1335,1357,1372,1380,1546|66,0:87|67,0:130,296,477,506,750,782,998,1219,1594,1670,1748,1796,2348,2810,3085,3213,3423,3507,3611,3632,3838,3845,3887,3922,4137,4324,4396,4551,4583,4630,4669,4731,4819,4876,4972,5116,5326,5334,5437,5490,5499,5559,5583,5596,5644,5809,6062,6499,6562,6699,6752,6815,6843,6851,7002,7480,7584,7837|68,0:107,209,1019,1396|69,0:219,275,514|70,0:165,241,307,476,541,570,613,1197|71,0:193,229,435,1034,1129,1394,1699,1961,1969,2022,2056,2064,2111,2141,2254|72,0:492,717,748,1339,1482|73,0:482,770,956,1405,1596,1753,1764,1929|74,8:129,252,308,364,376,447,461,480,503,570,731,903,1057,1109,1266,1337|75,8:136,240,281,327,340,368,397,471,497,509,525,590,651,672,740,807,963,1120,1169,1326,1397|76,0:93,377,617,642,987,1250,1509|77,0:77,369,940,1035,1399,1499,1852,1927,1997,2172,2209,2329,3067|78,8:109,136,300,391,495,527,565,718,770,838,896,992,1058,1159,1267|79,0:71,443,529,1159,1254,1751,1971,1980,2060,2556,2601,2922,3291,3378,3659,3695,3756,3864,3945,3972,4123,4474,4617,5051,5287,5301,5335|80,4:103,443,451,473,536,567,1238,1459,2682,3104,3282,3293,3342,3730,4069,4227,4762,5022,5071,5179,5200,5262,5410,5462,5557,5608,5657,5686|81,0:99,420,517,1118,1225,1625,1902,2233,2280,2676,2807,2943,3270,3366,3579|82,8:251,272,442,472,544,622,658,808,839,890,947,1018,1043,1091,1282,1315,1392,1420,1452,1465,1524,1540,1576,1657,1806,1893,1919,1966,2022,2061,2154,2302,2439,2466,2496,2568,2584,2620,2702,2716,2773|83,0:285,336,759,785,815,1132|84,0:626,759,952,1030,1066|85,0:321|86,0:84,144,699,864,1656|87,0:410,454,759,923,1112,1383,1393,2104,2185,2661,3376,4495|88,0:20,143,208,238,343,531,847,928,1077,1142,1172,1261,1275,1306,1608,1673,1703,1869,1889,1958,2001,2026,2090,2120,2129,2210,2282,2324,2337,2353,2529,2587,2880,3033,3087,3347,3414,3700,3765,3795,4060,4089,4185,4505,4568,4755,4764,4961,5027,5092,5122,5283,5649,5744,6149,6214,6244,6466,6913,6970,7008,7210,7303,7368,7398,7791,7818,7847,7909,8098,8237,8252,8508,8730,8795,8825,9109,9253,9398,9586,9681,9746,9776,9850,9886,10060,10403,10542,10549,10927,11034,11099,11129,11785,11877,12050,12133,12210,12267,12323,12388,12418,12624,12666,13081,13092,13123,13303,13336,13518,13615,13756,14268,14333,14363,14503,14605,14632,14932,14997,15027,15233,15256,15687,15703,15721,15776,16131,16205,16273,16440,16505,16535,16628,17071,17115,17338,17376,18029,18094,18124,18564,18679,18688,18999,19064,19094,19497,19513,19531,19586,19950,20264,20329,20359,20638,20690,20722,20783,20883,20915,20937,20982,21111,21150,21215,21280,21310,21665,21780,21789,22179,22311,22354,22383,22575,22671,22736,22766,23094,23127,23192,23222,23333,23440,23496,23548,23567,23614,23658,23674,23714,23768,23792,24135,24200,24230,24376,24504,24748,24802,24865,24907,24923,25259,25312,25422,25538,25603,25633,25723,25747,25766,25788,25830,25876,25943,25966,26029,26121,26270,26344,26388,26577,26607,26717,26735,26873,26912,27128,27193,27223,27312,27381,27405,27501,27552,27598,27670,27761,27780,27789,27872,28151,28183,28217,28380,28513,28578,28608,28781,29374,29802,29852,29917,29947,30172,30358,30398,30418,30519,30890,30955,30985,31144,31204,31352,31405,31416,31447,31753,31766,31776,31855,32132,32439,32627,32734,32799,32829,33293,33428,33605,33670,33700,33853,34020,34205|89,0:119,1796,1867,2184,2613,2958,3366,4101,4432|90,0:0,25,146,207,237,391,474,588,921,982,1012,1318,1389,1432,1457,1521,1604,1625,2313,2356,2417,2447,2780,2910,3020,3206,3253,3272,3302,3421,3471,3965,4075,4102,4213,4239,4300,4330,4500,4728,4756,5412,5473,5503,5638,5911,6108,6124,6163,6387,6404,6456,6470,6586,6867,7000,7043,7104,7134,7618,7826,7863,7904,7945,8129,8413,8497,8558,8588,9053,9264,9338,9459,9691,9999,10151,10175,10217,10254,10369,10378,10631,10692,10722,11004,11155,11330,11560,11621,11651,11804,11835,11942,11992,12004,12029,12384,12409,12446,12464,12476,12847,12926,13130,13191,13221,13408,13512,13571,13669,13711,13871,13914,13975,14005,14225,14267,14868,15070,15120,15321,15422,15482,15543,15573,15857,16010,16188,16417,16519,16612,16732,16876,16937,16967,17209,17455,17518,17616,18370,18421,18583,18680,18729,18790,18820,19023,19284,19322,19353,19871,19932,19962,20252,20291,21112,21301,21480,21518,21535|91,0:98,129,919,961,1148,1211,1499,1598,1639,1862,1893,2094,2150,2596,2796,2837,2871,2926,3046,3177,3216|93,0:272,302,1035,1065,1378,1408,1760,1841,1851,2029,2125,2712,2742,3179,3302,3452,3942,3972,4237,4291,4340,4522,4563,4726,5024,5054,5454,5948,6026,6201,6213,6374,6404,6625,7144,7177,7193,7569,7599,8373,8928,9383,9413,9571,9993,10171,10182,10230,10615,10952,11057,11087,11308,11837,12097,12146,12254,12275,12337,12485,12537,12632,12683,12800,12830,12932,12961,13604,13999,14465,14495,14634,15010,15369,15533,15664,16062,16194,16308,16338,16429,16461,16503,16626,16722,16782,16836,17160,17172,17302,17408,17542,17572,17812,17899,17907,18127,18163,18297,18417,18472,18850,18999,19032,19217,19242,19251,19329,19337,19624,19654,20118,20163,20384,21018,21192,21222,21326,21364,21919,21926,21968,22003,22218,22405,22477,22542,22697,22727,23056,23108,23121,23281,23339,23561,23623,23651,23659,23808,24084,24114,24486,24590,24843,24984,25024,25328,25477,25510,25526,25919,25949,26262,26294,26341,26380,26442,26530,26587,26683,26827,26931,26961,27132,27238,27327,27609,27790,28138,28168,28478,28554,28688,29103,29247,29255,29385"/></pk>