<?xml version="1.0" encoding="UTF-8" standalone="no"?>
<pk><wd nm="uick_Start_for_New_Users.pdf" rd="78,128:3477"/><wd nm="uick_start_for_new_users" rd="78,0:0"/><wd nm="uickest" rd="36,0:135"/><wd nm="uickly" rd="1,0:260|6,1:19,111|7,0:98,398,467|11,0:218|12,0:1015|14,0:82|15,0:92|17,0:1488|19,0:92|21,0:88|52,0:494|75,0:12018|77,0:1327,3657,3782,5653,11528,20279|78,0:1291"/><wd nm="uickpick" rd="10,0:2802|75,0:6369"/><wd nm="uide" rd="0,0:1319,1711,2450|7,0:371|8,0:37,259,313,387,427|19,0:1180|23,8:602,757,819,902,1044,1080|24,0:943|25,0:835,881,914,958|30,2:131,156,1777|34,2:120,145,1287|38,2:329,354,3122|52,0:354|53,0:424,672|74,0:247,2010,2053,2078,2161|75,0:1586,1813,1904,1948,2185,2873,9281,9953,12518,12615,12927,22953,30779,30815,33329,33364,33616,33682|77,0:153,927,1102,1275,1378,1619,2362,3454,3904,4117,4245,5418,6521,7121,7790,8771,8805,10375,11790,13443,13477,15085,16224,16479,18332,19457|78,0:3265|79,0:0|80,0:79,218,981,1324,1507,1685,1962,2022,2658,3888,4970,6320,7515,9329,11003,12746,14411,16207,16254,16735,17488,19570,21138,22643,24030,25865,26877,28084"/><wd nm="uide.pdf" rd="79,128:126"/><wd nm="uided" rd="14,0:1101|25,0:451|75,0:11655|77,0:5637|78,0:1598"/><wd nm="uides" rd="6,0:540,549|8,8:808,873,892,1019,1474|23,137:3,14,52,140,453,1017,1299|80,0:1867"/><wd nm="uild" rd="6,0:1479|9,8:658|19,0:1775|75,0:3220,3393|77,0:481,676,6034,6349,6464,6580,6671,14243,14323,15649"/><wd nm="uilder" rd="11,0:368,551,562,597|12,137:9,22,182,195,240,378,402,487,498,956,1156,1266,1325,1390,1574|14,0:247,335,512,526,570,1954|17,137:12,33,196,212,408,705,732,801,815,1429,1632,1748,1810,1886,2211|24,0:843,859,1218,1234|29,0:239|31,129:14,37,131,188,216,312,1000,1126,1167,1536,1651,1686,2234,2349,2384,2711,3352,4002|32,8:438,457,505|36,0:590,711,752|38,0:183,204|41,0:279,820|45,0:1144,1176,1217|46,0:1009|48,0:1718|49,0:501,536,795,4485|75,0:361,556,2351,2619,2862,2979,3143,9658,9853,9870,10060"/><wd nm="uilding" rd="9,0:414,611,903|11,0:474|12,0:348|23,0:541|54,0:2926|75,0:2607,2626,3365,3803,6149,9004|77,0:755,6836,14166,16060,16340,19690|80,0:18261"/><wd nm="uilt" rd="80,0:17873"/><wd nm="uing" rd="40,0:2006|74,0:786,1726|75,0:27436|78,0:571"/><wd nm="uip" rd="75,0:1822|77,0:1284"/><wd nm="uire" rd="51,0:427,707|58,0:1077|59,0:412,1143|78,0:2510|80,0:28697,28738"/><wd nm="uired" rd="67,0:3575|77,0:1317|80,0:10182,23281"/><wd nm="uiredinordertoutilizethisfeature" rd="76,0:544"/><wd nm="uirements" rd="44,0:1997,2104,3330|55,0:1090"/><wd nm="uires" rd="6,0:374|54,0:7792|80,0:24798"/><wd nm="uit" rd="43,0:996,1615,1814,1983,2169"/><wd nm="uite" rd="10,0:2888|11,0:1816|75,0:6454,25408|76,0:3643"/><wd nm="uiteallowsdistrictstoconfigurethecalleridthatappearsonarecipient" rd="76,0:275"/><wd nm="uitecalleridwithciscocallmanagerschoolmessengercommsuiteallowsdistrictstoconfigurethecalleridthatappearsonarecipient" rd="76,0:275"/><wd nm="uiteconfiguringcalleridwithciscocallmanagercopyright" rd="76,0:2086,2515,2860,3268,4003,4334"/><wd nm="uiz" rd="74,0:1794"/><wd nm="ukrainian" rd="3,0:869"/><wd nm="ul" rd="0,0:95|2,0:617|8,0:50,399|10,0:2720|19,0:2608|24,0:279|49,0:1757|54,0:401|74,0:273,2348,3882,4063,4173|75,0:6288,12734,14757|77,0:16093|80,0:1143,2561,2591,20737,20772,27040,29003"/><wd nm="ular" rd="9,0:940,1010,1092|31,8:512,1851,3294|54,0:4561,6303|55,0:438,1036|57,0:488,698,732|70,0:545,641|75,0:12119,13462,32569|77,0:6895,13083,13947,14733,14830,15619,15699|80,0:15849,26272"/><wd nm="ularly" rd="33,0:141|75,0:29592,29927|77,0:13190"/><wd nm="ulate" rd="75,0:30357|77,0:6175,6432,20124|80,0:14653"/><wd nm="ulated" rd="0,0:520|75,0:29320|77,0:9176"/><wd nm="ulating" rd="80,0:15032"/><wd nm="ulations" rd="44,0:370|78,0:2741"/><wd nm="ulators" rd="77,0:10938"/><wd nm="ulatory" rd="44,0:261|72,0:703"/><wd nm="ulb__exclamation" rd="0,0:1082|2,0:451|3,0:912|6,0:1228,2516|9,0:355|10,0:1277,1883|11,0:166|12,0:963|14,0:30,1169|15,0:40|17,0:1436|19,0:40,2727,3440|21,0:36|22,0:996|24,0:1003,1384|43,0:474|44,0:2348,2469,3057|47,0:1046,1894|48,0:974|49,0:607,1685,3094|50,0:636|51,0:649|54,0:2949|58,0:279|63,0:571|64,0:1216,1787,2508|65,0:151|67,0:1172|68,0:795,1714"/><wd nm="uld" rd="1,0:1054,1414,1636|2,0:659|3,0:962,1739|6,0:2000,2360,3758|8,0:616,1447|9,0:264|10,0:485|11,0:1239|13,0:242,865,1447|14,0:1764|15,0:463,1485|16,0:640|18,0:573,1778|19,0:504,928,1138,1242,1354,2096,3577,3919,4333|20,0:378|21,0:227,494|22,0:627|24,8:434,616,735,1164|25,0:773,1147,1357|26,0:288|29,0:396|30,0:828|31,0:1289,1405,1733,1764,1879,1996,2431,2475,2892,2923,2969,3088,3555,3774|33,0:264,461,1068,1216,1532,1761|35,0:292|36,0:222,3976|38,0:1297,2907|40,0:1566,1664,2059|41,0:682,789,909,1010|44,0:2291,3134|45,0:28,1187|46,0:871,978,1098,1199|47,0:478,2636|48,0:1580,1687,1807,1908,2282|49,0:3161,3467,3523|50,0:828|51,0:1456|52,0:1474|54,0:565,2803,2863,5404,7473|56,0:560|58,0:1386,1853,2014,2103|59,0:1334|60,0:462,614,1891|63,0:550|64,0:2812|65,0:466,706,1294|66,0:1418,3348,3370,4519,4609,4753,5029,5123|67,0:3429|68,0:2210,2467,2540,2611,2881,2935,3162,3408,3530|70,0:373,445,591|71,0:1023|73,0:1649|74,0:2241,2730,2922,3587,3850,4361|75,0:7946,11427,12573,12777,14077,15503,16337,16537,18403,19924,20109,20930,21637,21878,23224,26017,27192,27290,27489,29581,29635,30211,31638,33628|77,0:1727,1816,2207,6256,7672,8557,8655,10668,10953,17660,17793,18044,18134,18171,18542,18748,18842,19010,19363,20144|78,0:687,814,2591,2824,3074|80,0:3717,4131,4793,10036,13733,14604,15182,15738,15929,17804,18409,20697,20730,20818,21686,22534,24479,25240,25719,27095"/><wd nm="uldbeanystringofdigits" rd="76,0:1169"/><wd nm="ulddisplaythecalleridforthatcampus" rd="76,0:924"/><wd nm="uldexistforeachcalleridvaluethatneededtobeconfigured" rd="76,0:1796"/><wd nm="uldneedtohaveanentrythatmappedtheroutepatternprefixtotheappropriatecalleridvalueforthecampus" rd="76,0:1597"/><wd nm="ule" rd="0,0:627|1,0:794|6,0:1508,1591,1872|9,0:751,1255,1637,2119,2220|10,0:2934,3315|24,0:657|31,0:765,836,1465,2094,2133,2573,2612,3184,3223|33,8:204,275,383,496,740,1179,1423|44,0:429|53,0:737|54,0:860,2210|58,4:743,771,962,994|67,0:2299,2379,3845|68,0:2740,2865|70,0:985|74,0:2893|75,0:6500,6846|77,0:5294,13819,14457,14947,15393,15510,15815,15829,15848,15943|80,0:8690,8770,10450,15597,15722"/><wd nm="uled" rd="1,0:1894|5,0:270|33,8:78,618|36,0:3947|64,0:940,1035|67,0:5461|69,0:544,1043,1091,1966,2022,2439,2716,2773|75,0:29690,29936|77,0:13127|80,0:12254"/><wd nm="ules" rd="6,0:1494,1531|9,137:14,45,237,673,679,833,921,1027,1871,2570|10,4:252,2607,2633,3015,3033,3057,3169,3649|11,0:817,1223,1343,1663,1740,1873|66,0:2613|70,8:714,800,805,897,1124|75,0:481,2649,3271,3424,3912,5320,6176,6201,6585,6697,7180,28592|77,0:496,669,691,3101,6364,6595,6686,6695,6782,6853,13663,13701,13916,14137,14258,14338,14399,14540,14679,14759,15596,16080,16414|80,0:20175,28037"/><wd nm="uling" rd="5,129:0,30,334,569|31,0:880,914|32,0:883,935|33,129:9,37,525,559,2079|36,0:3286|75,0:32929"/><wd nm="ulk" rd="21,0:330|44,0:290|77,0:10649"/><wd nm="ull" rd="35,0:310,413|36,0:2701|38,0:1603|54,0:4444,5237|64,0:2164|77,0:9456|80,0:26155"/><wd nm="ulletins" rd="75,0:25893"/><wd nm="ully" rd="33,0:1002|38,0:1360|54,0:1016|69,0:1881|77,0:5804"/><wd nm="ult" rd="2,0:725|3,0:239,988,1698|11,0:655|12,0:437|15,0:1608,2016|19,0:2219,2685,3185|25,0:729|26,0:338,1379|27,0:979|30,0:833,1712,1727|31,0:2952|33,0:945|34,0:1222,1237|38,0:1302,1518,2923,3057,3072|49,4:2407,3430|55,0:707|58,0:1552,1591|60,0:1906|61,0:97|62,0:105|63,0:892,1155,1414|64,0:549,2018,2094,2845,2879|66,0:1863,4962|74,0:775|75,0:3152,14200,14834,15245,18710,19114,31817|77,0:8189,8505,12702,16995,18507,18590,18717,18796,18819,18988,20240|80,0:4584,5974,16689,19024,19226,19314,20983,29218,29315"/><wd nm="ultaneously" rd="77,0:4871"/><wd nm="ulted" rd="31,0:1807"/><wd nm="ulti" rd="67,0:2881|80,0:9488"/><wd nm="ultilingual" rd="25,0:296,1319|26,129:15,47,646,741,1838|27,0:365|55,0:1078|67,0:2924|77,0:8730|80,0:9531"/><wd nm="ultimodal" rd="80,0:2949"/><wd nm="ultiple" rd="1,0:1482|9,0:1863|24,0:531|25,0:1261,1415|26,0:256|31,0:3010|43,0:822|65,0:683|68,0:2242|70,0:1001|75,0:9741|77,0:8587,18198,21181|80,0:2907,17129"/><wd nm="ults" rd="2,0:554|3,0:951,1728|10,0:2485|15,0:1343|18,0:1556|30,2:144,177,1160,1753,1790|31,0:1049,1940,2080,2559,3170,3844|32,0:153,237,573,809,838|33,0:1639,1794,1880,1918|34,2:133,192,674,1263,1300|36,0:83,1407,2599|37,8:178,251,393,1056,1073|38,2:291,342,401,720,2374,3098,3135|54,0:140,5819|60,0:780|66,0:1761|70,0:1324|71,0:141|75,0:6026,18301,21461,31871,32792,32870,32965,33009|77,0:839,10281,12102,13237,18499|78,0:3197"/><wd nm="uly" rd="74,0:2300,3486,3906"/><wd nm="um" rd="1,0:494|64,0:1335,1367,1435,1467|66,0:4280,4310,4359,4389|67,0:3818|75,0:31753|77,0:17448,17531|80,0:10423,28243,28265"/><wd nm="umber" rd="6,0:1418,2948,3057|9,0:1275,1307,1657,1689,2240,2272|10,0:2236,2245,2406,2415|11,0:1073,1621,1648|13,0:1235|18,0:1974|25,0:758|26,0:88,582,1028,1065,1129,1432|27,0:92,619,656,720,1032|29,0:342|30,0:1326,1608|31,0:3504,3516|33,0:982|34,0:828,1069,1118|36,0:2042,2102,2180,2541,2718,3056,3166,3371,3574|37,0:980,1600,1648|38,0:645,853,938,1077,1149,1527,1620,1958,2540,2769,2818,2862|43,0:362|44,0:624,936,1305,1437,1785,3430|54,0:4861,5283|58,0:1682,1723,1816,1884|62,8:81,708,888,931,1158|64,0:1374,1474|65,0:1256|66,0:2110,2563,3416,4317,4396,4466,4585,4699,4800|67,0:1734,2476,3825,5551|68,0:2646,2695,2785|69,0:867,1792|71,0:1057|75,0:5615,5624,5947,5956,8260,10818,21833,31021,31055,31453,31608,31760,32584,32726|76,0:1244|77,0:4826,7881,8358,13098,14966,14998,15412,15444,15962,15994,17029,17099,17647,18248,18826,18995,19074,19219|78,0:1186,1273,2044,2087|80,0:8129,8867,10430,12344,15262,15552,15642,19465,20125,22558,25805,26572"/><wd nm="umbercalleridforthecampusroutepatternprefixrecipient" rd="76,0:1344"/><wd nm="umberingplan" rd="76,0:3723"/><wd nm="umberneedingtobedialedstringthatwillbesenttocallmanagerlincolnhighschool" rd="76,0:1418"/><wd nm="umbers" rd="13,0:1170|33,0:1318|36,0:2115,3202,3272,3352,3412,3431,3481,3491,3619,3793,3864|38,0:1018|54,0:7300,7424|58,0:1149,1163,1613,2002,2091|62,137:13,35,207,490,570,658,679,759,823,982,1132,1624|65,8:48,144,316,353,407,511,657,699,763,825,883,941,1026,1046,1175|67,0:4005,4689,5756|71,0:1096|75,0:8190,8624|77,0:12602,13058,17612,17708,17756,17871,18892|78,0:1376|80,0:3274,3295,10608,11488,12549,24306,24430,29372,29399"/></pk>